langchain_perigon/__init__.py
langchain_perigon/articles_retriever.py
langchain_perigon/types/__init__.py
langchain_perigon/wikipedia_retriever.py
langchain_perigon-0.1.1.dist-info/METADATA
langchain_perigon-0.1.1.dist-info/WHEEL
langchain_perigon-0.1.1.dist-info/RECORD
