Metadata-Version: 2.4
Name: langchain-perigon
Version: 0.1.1
Summary: An integration package connecting Perigon and LangChain
License: MIT
Keywords: langchain,perigon,ai,llm,retrieval
Author: Islem Maboud
Author-email: islem@perigon.io
Requires-Python: >=3.11,<4.0
Classifier: Development Status :: 3 - Alpha
Classifier: Intended Audience :: Developers
Classifier: License :: OSI Approved :: MIT License
Classifier: Programming Language :: Python :: 3
Classifier: Programming Language :: Python :: 3.11
Classifier: Programming Language :: Python :: 3.12
Classifier: Programming Language :: Python :: 3.13
Classifier: Programming Language :: Python :: 3.14
Classifier: Topic :: Scientific/Engineering :: Artificial Intelligence
Classifier: Topic :: Software Development :: Libraries :: Python Modules
Requires-Dist: langchain (>=0.3.27,<0.4.0)
Requires-Dist: langchain-core (>=0.3.76,<0.4.0)
Requires-Dist: langchain-tests (>=0.3.21,<0.4.0)
Requires-Dist: perigon (>=1.0.0,<2.0.0)
Project-URL: Homepage, https://github.com/goperigon/langchain-perigon
Project-URL: Repository, https://github.com/goperigon/langchain-perigon
